Workbook

Sheet Dados_Mensais
A1: Mês | B1: Volume Vendido (m³) | C1: Pedidos | D1: Preço Médio (R$/m³) | E1: Receita Concreto (R$) | F1: Receita Bombeamento (R$) | G1: Receita Frete (R$) | H1: Receita Total (R$) | I1: Custo Operacional (R$) | J1: Lucro Líquido (R$) | K1: Margem Líquida (%) | L1: Custo por m³ (R$) | M1: Ticket Médio (R$) | N1: Dias Trabalhados | O1: Tempo Médio Espera (min)
A2: 46023 | B2: 1650 | C2: 188 | D2: 380 | E2: 627000 | F2: 53.088874 | G2: 2077.411 | H2: 629130.5 | I2: 475667.69 | J2: 153462.81 | K2: 0.24392843 | L2: 288.28345 | M2: 3346.4388 | N2: 25 | O2: 30
A3: 46054 | B3: 1720 | C3: 195 | D3: 382 | E3: 657040 | F3: 65.781842 | G3: 2081.4061 | H3: 659187.19 | I3: 493153.18 | J3: 166034.01 | K3: 0.25187687 | L3: 286.71697 | M3: 3380.4471 | N3: 24 | O3: 27
A4: 46082 | B4: 1810 | C4: 223 | D4: 385 | E4: 696850 | F4: 60.867814 | G4: 2610.0004 | H4: 699520.87 | I4: 519429.36 | J4: 180091.51 | K4: 0.2574498 | L4: 286.97755 | M4: 3136.8649 | N4: 26 | O4: 40
A5: 46113 | B5: 1760 | C5: 213 | D5: 384 | E5: 675840 | F5: 63.579753 | G5: 2581.3174 | H5: 678484.9 | I5: 518864.57 | J5: 159620.32 | K5: 0.23525995 | L5: 294.80942 | M5: 3185.3751 | N5: 25 | O5: 32
A6: 46143 | B6: 1880 | C6: 213 | D6: 388 | E6: 729440 | F6: 64.637697 | G6: 2302.7343 | H6: 731807.37 | I6: 531812.82 | J6: 199994.56 | K6: 0.27328852 | L6: 282.87916 | M6: 3435.7154 | N6: 26 | O6: 37
A7: 46174 | B7: 1950 | C7: 240 | D7: 390 | E7: 760500 | F7: 67.586008 | G7: 2692.3101 | H7: 763259.9 | I7: 573392.72 | J7: 189867.18 | K7: 0.24875823 | L7: 294.04755 | M7: 3180.2496 | N7: 25 | O7: 35
A8: 46204 | B8: 2020 | C8: 225 | D8: 392 | E8: 791840 | F8: 74.958407 | G8: 2603.8026 | H8: 794518.76 | I8: 576880.5 | J8: 217638.26 | K8: 0.27392463 | L8: 285.58441 | M8: 3531.1945 | N8: 26 | O8: 39
A9: 46235 | B9: 2100 | C9: 259 | D9: 395 | E9: 829500 | F9: 71.509721 | G9: 3045.1354 | H9: 832616.65 | I9: 607462.06 | J9: 225154.59 | K9: 0.27041807 | L9: 289.26765 | M9: 3214.7361 | N9: 26 | O9: 38
A10: 46266 | B10: 2050 | C10: 236 | D10: 394 | E10: 807700 | F10: 75.710606 | G10: 2499.6291 | H10: 810275.34 | I10: 612474.22 | J10: 197801.12 | K10: 0.24411593 | L10: 298.76791 | M10: 3433.3701 | N10: 25 | O10: 36
A11: 46296 | B11: 2180 | C11: 237 | D11: 398 | E11: 867640 | F11: 82.812148 | G11: 2899.2133 | H11: 870622.03 | I11: 652788 | J11: 217834.03 | K11: 0.25020505 | L11: 299.44404 | M11: 3673.5107 | N11: 26 | O11: 41
A12: 46327 | B12: 2250 | C12: 257 | D12: 400 | E12: 900000 | F12: 77.746107 | G12: 2888.773 | H12: 902966.52 | I12: 683202.27 | J12: 219764.25 | K12: 0.24338028 | L12: 303.64546 | M12: 3513.4884 | N12: 25 | O12: 35
A13: 46357 | B13: 2380 | C13: 269 | D13: 405 | E13: 963900 | F13: 87.547904 | G13: 2862.9146 | H13: 966850.46 | I13: 715083.44 | J13: 251767.02 | K13: 0.26039913 | L13: 300.45523 | M13: 3594.2396 | N13: 26 | O13: 34

Sheet Dashboard
B2: DASHBOARD — USINA DE CONCRETO
B3: Análise mensal — dados simulados para portfólio de Analytics
B5: Receita Total | D5: Volume Vendido | F5: Lucro Líquido | H5: Margem Média
B6: =SUM(Dados_Mensais!H2:H13) | D6: =SUM(Dados_Mensais!B2:B13) | F6: =SUM(Dados_Mensais!J2:J13) | H6: =AVERAGE(Dados_Mensais!K2:K13)
B23: Resumo Mensal
B24: Mês | C24: Receita Total | D24: Lucro Líquido | E24: Margem | F24: Volume (m³)
B25: =Dados_Mensais!A2 | C25: =Dados_Mensais!H2 | D25: =Dados_Mensais!J2 | E25: =Dados_Mensais!K2 | F25: =Dados_Mensais!B2
B26: =Dados_Mensais!A3 | C26: =Dados_Mensais!H3 | D26: =Dados_Mensais!J3 | E26: =Dados_Mensais!K3 | F26: =Dados_Mensais!B3
B27: =Dados_Mensais!A4 | C27: =Dados_Mensais!H4 | D27: =Dados_Mensais!J4 | E27: =Dados_Mensais!K4 | F27: =Dados_Mensais!B4
B28: =Dados_Mensais!A5 | C28: =Dados_Mensais!H5 | D28: =Dados_Mensais!J5 | E28: =Dados_Mensais!K5 | F28: =Dados_Mensais!B5
B29: =Dados_Mensais!A6 | C29: =Dados_Mensais!H6 | D29: =Dados_Mensais!J6 | E29: =Dados_Mensais!K6 | F29: =Dados_Mensais!B6
B30: =Dados_Mensais!A7 | C30: =Dados_Mensais!H7 | D30: =Dados_Mensais!J7 | E30: =Dados_Mensais!K7 | F30: =Dados_Mensais!B7
B31: =Dados_Mensais!A8 | C31: =Dados_Mensais!H8 | D31: =Dados_Mensais!J8 | E31: =Dados_Mensais!K8 | F31: =Dados_Mensais!B8
B32: =Dados_Mensais!A9 | C32: =Dados_Mensais!H9 | D32: =Dados_Mensais!J9 | E32: =Dados_Mensais!K9 | F32: =Dados_Mensais!B9
B33: =Dados_Mensais!A10 | C33: =Dados_Mensais!H10 | D33: =Dados_Mensais!J10 | E33: =Dados_Mensais!K10 | F33: =Dados_Mensais!B10
B34: =Dados_Mensais!A11 | C34: =Dados_Mensais!H11 | D34: =Dados_Mensais!J11 | E34: =Dados_Mensais!K11 | F34: =Dados_Mensais!B11
B35: =Dados_Mensais!A12 | C35: =Dados_Mensais!H12 | D35: =Dados_Mensais!J12 | E35: =Dados_Mensais!K12 | F35: =Dados_Mensais!B12
B36: =Dados_Mensais!A13 | C36: =Dados_Mensais!H13 | D36: =Dados_Mensais!J13 | E36: =Dados_Mensais!K13 | F36: =Dados_Mensais!B13

Sheet README
A1: PROJETO — ANÁLISE DE DADOS | USINA DE CONCRETO
A3: Objetivo | B3: Demonstrar uma análise mensal de indicadores comerciais, operacionais e financeiros de uma usina de concreto.
A4: Origem dos dados | B4: Dados simulados/ilustrativos, construídos para fins de portfólio e estudo de Analytics.
A5: Período | B5: Janeiro a Dezembro de 2026.
A6: Principais KPIs | B6: Receita Total, Volume Vendido, Lucro Líquido e Margem Líquida.
A7: Análises | B7: Evolução mensal, volume vendido, receita, custos, lucro, margem e eficiência operacional.
A8: Uso sugerido | B8: Abrir a aba Dashboard e utilizar os dados da aba Dados_Mensais para criar segmentações, gráficos e indicadores adicionais no Excel.
